Metadata-Version: 1.0
Name: Binomialdistributions2021
Version: 0.1
Summary: Binomial distributions ToTry
Home-page: UNKNOWN
Author: UNKNOWN
Author-email: UNKNOWN
License: UNKNOWN
Platform: UNKNOWN
